{"assets/images/.DS_Store":["assets/images/.DS_Store"],"assets/images/logo1.png":["assets/images/logo1.png"],"assets/images/logo2.png":["assets/images/logo2.png"],"assets/images/logo3.png":["assets/images/logo3.png"],"assets/images/logo4.png":["assets/images/logo4.png"],"assets/images/logo5.png":["assets/images/logo5.png"],"assets/images/onboarding.png":["assets/images/onboarding.png"],"assets/images/shoes1.png":["assets/images/shoes1.png"],"assets/images/shoes2.png":["assets/images/shoes2.png"],"assets/images/shoes3.png":["assets/images/shoes3.png"],"assets/images/shoes4.png":["assets/images/shoes4.png"],"packages/cupertino_icons/assets/CupertinoIcons.ttf":["packages/cupertino_icons/assets/CupertinoIcons.ttf"]}